{
  "seller": {
    "name": "VISTA REALTY SERVICES",
    "name_short": "VISTA REALTY",
    "addr1": "Plot 836, MIDC Area",
    "addr2": "Taloja, Navi Mumbai - 443761",
    "gstin": "27PRNEF8302F1Z8",
    "state_name": "Maharashtra",
    "state_code": "27",
    "email": "accounts25@vistarealty.com",
    "pan": "EQCEJ4155Z"
  },
  "buyer": {
    "name": "GREENFIELD LOGISTICS",
    "address": "Flat 295, Sector 26, Mumbai - 425892",
    "gstin": "27TLOLM3313W1Z1",
    "state_name": "Maharashtra",
    "state_code": "27"
  },
  "invoice": {
    "no": "INV-183",
    "date": "17-Sep-24",
    "delivery_note": "",
    "payment_terms": "Immediate",
    "supplier_ref": "",
    "other_ref": "",
    "order_no": "PO-9744",
    "order_date": "08-Sep-24",
    "dispatch_doc": "",
    "delivery_note_date": "",
    "dispatch_through": "Courier",
    "destination": "Thane",
    "delivery_terms": ""
  },
  "items": [
    {
      "particulars": "Office Rent",
      "hsn": "999599",
      "qty": "10",
      "rate": 4146,
      "amount": 41460
    },
    {
      "particulars": "Office Rent",
      "hsn": "999599",
      "qty": "5",
      "rate": 4755,
      "amount": 23775
    }
  ],
  "totals": {
    "subtotal": 65235,
    "taxable_total": 65235,
    "cgst_total": 0.0,
    "sgst_total": 0.0,
    "tax_total": 0.0
  },
  "tax_rows": [
    {
      "hsn": "999599",
      "taxable": 65235,
      "cgst_rate": 0.0,
      "cgst_amt": 0.0,
      "sgst_rate": 0.0,
      "sgst_amt": 0.0
    }
  ],
  "amount_in_words": "INR Sixty-Five Thousand, Two Hundred And Thirty-Five Only",
  "tax_amount_in_words": "INR Zero Only",
  "remarks": "Goods supplied as per order.",
  "bank": {
    "name": "ICICI BANK",
    "acno": "86160254688",
    "branch_ifsc": "PUNE – ICIC0000456",
    "swift": "ICICINBBXXX"
  },
  "_meta": {
    "gst_slab": 0,
    "generated_id": 23
  }
}