{
  "seller": {
    "name": "VISTA REALTY SERVICES",
    "name_short": "VISTA REALTY",
    "addr1": "Plot 472, MIDC Area",
    "addr2": "Taloja, Navi Mumbai - 456626",
    "gstin": "27KYWAT3015K1Z9",
    "state_name": "Maharashtra",
    "state_code": "27",
    "email": "accounts66@vistarealty.com",
    "pan": "PUTSN3229X"
  },
  "buyer": {
    "name": "UNITY CONSTRUCTIONS",
    "address": "Flat 380, Sector 15, Mumbai - 440980",
    "gstin": "27DDCPN6224E1Z8",
    "state_name": "Maharashtra",
    "state_code": "27"
  },
  "invoice": {
    "no": "T-668",
    "date": "03-Jun-24",
    "delivery_note": "",
    "payment_terms": "15 Days",
    "supplier_ref": "",
    "other_ref": "",
    "order_no": "PO-7872",
    "order_date": "01-Jun-24",
    "dispatch_doc": "",
    "delivery_note_date": "",
    "dispatch_through": "Hand Delivery",
    "destination": "Navi Mumbai",
    "delivery_terms": "Ex-Works"
  },
  "items": [
    {
      "particulars": "Consulting Services",
      "hsn": "998312",
      "qty": "10",
      "rate": 4775,
      "amount": 47750
    },
    {
      "particulars": "Office Rent",
      "hsn": "999599",
      "qty": "3",
      "rate": 4568,
      "amount": 13704
    },
    {
      "particulars": "Furniture Purchase",
      "hsn": "940330",
      "qty": "1",
      "rate": 1132,
      "amount": 1132
    },
    {
      "particulars": "Consulting Services",
      "hsn": "998312",
      "qty": "1",
      "rate": 1264,
      "amount": 1264
    },
    {
      "particulars": "Electrical Supplies",
      "hsn": "853690",
      "qty": "10",
      "rate": 3852,
      "amount": 38520
    }
  ],
  "totals": {
    "subtotal": 102370,
    "taxable_total": 102370,
    "cgst_total": 14331.8,
    "sgst_total": 14331.8,
    "tax_total": 28663.6
  },
  "tax_rows": [
    {
      "hsn": "998312",
      "taxable": 102370,
      "cgst_rate": 14.0,
      "cgst_amt": 14331.8,
      "sgst_rate": 14.0,
      "sgst_amt": 14331.8
    }
  ],
  "amount_in_words": "INR One Lakh, Thirty-One Thousand And Thirty-Four Only",
  "tax_amount_in_words": "INR Twenty-Eight Thousand, Six Hundred And Sixty-Four Only",
  "remarks": "Subscription renewal invoice.",
  "bank": {
    "name": "STATE BANK OF INDIA",
    "acno": "18646190464",
    "branch_ifsc": "TALOJA – SBIN0012984",
    "swift": "SBININBBXXX"
  },
  "_meta": {
    "gst_slab": 28,
    "generated_id": 189
  }
}